command_v11_client/__init__.py
command_v11_client/client.py
command_v11_client/errors.py
command_v11_client/keyfactor.py
command_v11_client/py.typed
command_v11_client/types.py
command_v11_client/api/__init__.py
command_v11_client/api/agent/__init__.py
command_v11_client/api/agent/get_agents.py
command_v11_client/api/agent/get_agents_id.py
command_v11_client/api/agent/post_agents_approve.py
command_v11_client/api/agent/post_agents_disapprove.py
command_v11_client/api/agent/post_agents_id_fetch_logs.py
command_v11_client/api/agent/post_agents_id_reset.py
command_v11_client/api/agent/post_agents_reset.py
command_v11_client/api/agent/post_agents_set_auth_certificate_reenrollment.py
command_v11_client/api/agent_blueprint/__init__.py
command_v11_client/api/agent_blueprint/delete_agent_blue_print_id.py
command_v11_client/api/agent_blueprint/get_agent_blue_print.py
command_v11_client/api/agent_blueprint/get_agent_blue_print_id.py
command_v11_client/api/agent_blueprint/get_agent_blue_print_id_jobs.py
command_v11_client/api/agent_blueprint/get_agent_blue_print_id_stores.py
command_v11_client/api/agent_blueprint/post_agent_blue_print_apply_blueprint.py
command_v11_client/api/agent_blueprint/post_agent_blue_print_generate_blue_print.py
command_v11_client/api/agent_pool/__init__.py
command_v11_client/api/agent_pool/delete_agent_pools_id.py
command_v11_client/api/agent_pool/get_agent_pools.py
command_v11_client/api/agent_pool/get_agent_pools_agents.py
command_v11_client/api/agent_pool/get_agent_pools_id.py
command_v11_client/api/agent_pool/post_agent_pools.py
command_v11_client/api/agent_pool/put_agent_pools.py
command_v11_client/api/app_setting/__init__.py
command_v11_client/api/app_setting/get_app_setting.py
command_v11_client/api/app_setting/get_app_setting_id.py
command_v11_client/api/app_setting/put_app_setting.py
command_v11_client/api/app_setting/put_app_setting_id_set.py
command_v11_client/api/app_setting/put_app_setting_name_set.py
keyfactor_command_sdk-11.0.0a1.dist-info/LICENSE
keyfactor_command_sdk-11.0.0a1.dist-info/METADATA
keyfactor_command_sdk-11.0.0a1.dist-info/WHEEL
keyfactor_command_sdk-11.0.0a1.dist-info/top_level.txt
keyfactor_command_sdk-11.0.0a1.dist-info/RECORD
