Metadata-Version: 2.1
Name: keyfactor-command-sdk
Version: 11.0.0a1
Summary: SDK in Python for Command 11.x Web APIs.
Author-email: "Keyfactor Inc." <no-reply@keyfactor.com>
License: Apache License
Project-URL: Homepage, https://github.com/Keyfactor/command-11-python-client-sdk
Project-URL: Repository, https://github.com/Keyfactor/command-11-python-client-sdk
Project-URL: Documentation, https://github.com/Keyfactor/command-11-python-client-sdk#readme
Keywords: keyfactor,sdk,api
Classifier: Programming Language :: Python :: 3
Classifier: License :: OSI Approved :: Apache Software License
Classifier: Operating System :: OS Independent
Classifier: Development Status :: 3 - Alpha
Classifier: Intended Audience :: Developers
Classifier: Topic :: Software Development :: Libraries :: Python Modules
License-File: LICENSE
Requires-Dist: requests
Requires-Dist: httpx
Requires-Dist: oauthlib
Requires-Dist: attrs
Requires-Dist: python-dateutil
